django_resumable_async_upload/__init__.py
django_resumable_async_upload/fields.py
django_resumable_async_upload/files.py
django_resumable_async_upload/models.py
django_resumable_async_upload/py.typed
django_resumable_async_upload/static/admin_resumable/js/resumable.js
django_resumable_async_upload/storage.py
django_resumable_async_upload/templates/admin_resumable/admin_file_input.html
django_resumable_async_upload/templates/admin_resumable/user_file_input.html
django_resumable_async_upload/urls.py
django_resumable_async_upload/validators.py
django_resumable_async_upload/views.py
django_resumable_async_upload/widgets.py
django_resumable_async_upload-0.1.4.dist-info/WHEEL
django_resumable_async_upload-0.1.4.dist-info/METADATA
django_resumable_async_upload-0.1.4.dist-info/RECORD
