Metadata-Version: 2.3
Name: django-resumable-async-upload
Version: 0.1.4
Summary: A Django app for the uploading of large files from the django admin site.
Author: Paige Williams
Author-email: Paige Williams <pwilliams@ecotrust.org>
Classifier: Environment :: Web Environment
Classifier: Framework :: Django
Classifier: Intended Audience :: Developers
Classifier: License :: OSI Approved :: MIT License
Classifier: Operating System :: OS Independent
Classifier: Programming Language :: Python
Classifier: Programming Language :: Python :: 3.12
Classifier: Topic :: Internet :: WWW/HTTP
Classifier: Topic :: Internet :: WWW/HTTP :: Dynamic Content
Requires-Dist: django>=3.0.14
Requires-Python: >=3.10
Project-URL: Homepage, https://github.com/Ecotrust/django-resumable-async-upload
Project-URL: Issues, https://github.com/Ecotrust/django-resumable-async-upload/issues
